{
    "changelog": [
        {
            "comments": [
                "Migrated from v1.4"
            ],
            "version": "2.0"
        }
    ],
    "cluster": {
        "biosyn_class": [
            "Terpene"
        ],
        "compounds": [
            {
                "compound": "monoterpenes-diterpenes",
                "database_id": []
            }
        ],
        "genes": {
            "annotations": [
                {
                    "comments": "cis-prenyl transferase 8",
                    "id": "AUTOORF_00001"
                },
                {
                    "comments": "cis-prenyl transferase 9",
                    "id": "AUTOORF_00002"
                },
                {
                    "comments": "alcohol acyltransferase 1",
                    "id": "AUTOORF_00003"
                }
            ],
            "extra_genes": [
                {
                    "id": "AUTOORF_00001",
                    "location": {
                        "exons": [
                            {
                                "end": 41978,
                                "start": 41888
                            },
                            {
                                "end": 42385,
                                "start": 42060
                            }
                        ],
                        "strand": 1
                    },
                    "translation": "MSSLVLQCWKLSSPSLFLQQNTSISMGAFKGIHKLQIPNSPMTVSARGLNKISCSLSLQTEKLCYEGNDNDLDEELMPKHIALIMDGNRRWAKDKGLEVYEGHKHIIPKLKEICDISSKLGIQIITAFAFSTENWKRSK"
                },
                {
                    "id": "AUTOORF_00002",
                    "location": {
                        "exons": [
                            {
                                "end": 86338,
                                "start": 86276
                            },
                            {
                                "end": 84097,
                                "start": 83764
                            }
                        ],
                        "strand": -1
                    },
                    "translation": "MGLKKKRKRMGKKNRKRGWGETSPCDCTKLWWIL"
                },
                {
                    "id": "AUTOORF_00003",
                    "location": {
                        "exons": [
                            {
                                "end": 100291,
                                "start": 99528
                            }
                        ],
                        "strand": 1
                    },
                    "translation": "IFLNALSELI"
                }
            ]
        },
        "loci": {
            "accession": "KC807996.1",
            "completeness": "Unknown",
            "evidence": [],
            "organism": "Solanum pimpinellifolium",
            "taxonomy": [
                "Eukaryota",
                "Viridiplantae",
                "Streptophyta",
                "Embryophyta",
                "Tracheophyta",
                "Spermatophyta",
                "Magnoliophyta",
                "eudicotyledons",
                "Gunneridae",
                "Pentapetalae",
                "asterids",
                "lamiids",
                "Solanales",
                "Solanaceae",
                "Solanoideae",
                "Solaneae",
                "Solanum",
                "Lycopersicon"
            ]
        },
        "mibig_accession": "BGC0001324",
        "minimal": true,
        "publications": [
            "pubmed:23757397"
        ]
    },
    "submitter": {
        "email": "info@mibig.secondarymetabolites.org",
        "institution": "MIBiG",
        "name": "mibig.secondarymetabolites.org"
    }
}