{
    "changelog": [
        {
            "comment": "Submitted",
            "version": "2.0"
        }
    ],
    "cluster": {
        "biosyn_class": [
            "NRP"
        ],
        "compounds": [
            {
                "compound": "paenibacterin",
                "database_id": []
            }
        ],
        "loci": {
            "accession": "JX899679.1",
            "completeness": "Unknown",
            "evidence": []
        },
        "mibig_accession": "BGC0000400",
        "minimal": true,
        "publications": [
            "pubmed:24607714"
        ]
    },
    "submitter": {
        "email": "info@mibig.secondarymetabolites.org",
        "institution": "MIBiG",
        "name": "mibig.secondarymetabolites.org"
    }
}