{
    "changelog": [
        {
            "comment": "Submitted",
            "version": "2.0"
        }
    ],
    "cluster": {
        "biosyn_class": [
            "Alkaloid"
        ],
        "compounds": [
            {
                "chem_struct": "C[C@@H]1[C@@H](SC2=CC=CC3=C2C1=CN3)C(=O)O",
                "compound": "chuangxinmycin",
                "database_id": []
            }
        ],
        "loci": {
            "accession": "MG824991.1",
            "completeness": "Unknown",
            "end_coord": 10917,
            "evidence": [],
            "organism": "Actinoplanes tsinanensis",
            "start_coord": 1,
            "taxonomy": [
                "Bacteria",
                "Actinobacteria",
                "Micromonosporales",
                "Micromonosporaceae",
                "Actinoplanes"
            ]
        },
        "mibig_accession": "BGC0001546",
        "minimal": true,
        "publications": [
            "pubmed:29565122"
        ]
    },
    "submitter": {
        "email": "info@mibig.secondarymetabolites.org",
        "institution": "MIBiG",
        "name": "mibig.secondarymetabolites.org"
    }
}