{
    "changelog": [
        {
            "comments": [
                "Migrated from v1.4"
            ],
            "version": "2.0"
        }
    ],
    "cluster": {
        "biosyn_class": [
            "Polyketide"
        ],
        "compounds": [
            {
                "compound": "6-hydroxymellein",
                "database_id": []
            }
        ],
        "loci": {
            "accession": "MG777496.1",
            "completeness": "Unknown",
            "end_coord": 29885,
            "evidence": [],
            "organism": "Cladonia uncialis subsp. uncialis",
            "start_coord": 7141,
            "taxonomy": [
                "Eukaryota",
                "Fungi",
                "Dikarya",
                "Ascomycota",
                "Pezizomycotina",
                "Lecanoromycetes",
                "OSLEUM clade",
                "Lecanoromycetidae",
                "Lecanorales",
                "Lecanorineae",
                "Cladoniaceae",
                "Cladonia"
            ]
        },
        "mibig_accession": "BGC0001489",
        "minimal": true,
        "polyketide": {},
        "publications": [
            "pubmed:0"
        ]
    },
    "submitter": {
        "email": "info@mibig.secondarymetabolites.org",
        "institution": "MIBiG",
        "name": "mibig.secondarymetabolites.org"
    }
}