{
    "general_params": {
        "compounds": [
            {
                "compound": "S-layer glycan"
            }
        ],
        "loci": {
            "accession": "AY442352.1",
            "conn_comp_cluster": [
                "Unknown"
            ],
            "complete": "Unknown"
        },
        "mibig_accession": "BGC0000795",
        "publications": [
            "pubmed:11096116",
            "pubmed:12740380",
            "pubmed:15316277",
            "pubmed:15044388",
            "pubmed:18336801"
        ],
        "minimal": true,
        "biosyn_class": [
            "Saccharide"
        ]
    },
    "personal": {
        "submitter_name": "mibig.secondarymetabolites.org",
        "submitter_institution": "MIBiG",
        "submitter_email": "info@mibig.secondarymetabolites.org"
    },
    "changelogs": [
        {
            "version": "2.0",
            "comment": "Submitted"
        }
    ]
}