{
    "general_params": {
        "Polyketide": {
            "pks_subclass": [
                "Modular Type I"
            ]
        },
        "biosyn_class": [
            "Polyketide"
        ],
        "compounds": [
            {
                "compound": "primycin"
            }
        ],
        "loci": {
            "nucl_acc": [
                {
                    "Accession": "AHBX01000216",
                    "end_coord": 183316,
                    "start_coord": 70636
                }
            ]
        },
        "mibig_accession": "BGC0001447",
        "minimal": true
    }
}