{
    "general_params": {
        "compounds": [
            {
                "compound": "putisolvin",
                "evidence_struct": [
                    "Other"
                ],
                "chem_act": [
                    "Unknown"
                ]
            }
        ],
        "loci": {
            "nucl_acc": [
                {
                    "accession": "DQ151887.2"
                }
            ],
            "conn_comp_cluster": [
                "Other"
            ],
            "complete": "unknown"
        },
        "mibig_accession": "BGC0000411",
        "publications": [
            "pubmed:16585751",
            "pubmed:18599835"
        ],
        "minimal": true,
        "biosyn_class": [
            "NRP"
        ]
    },
    "created": "2019-04-01T00:52:06+02:00",
    "modified": "2019-04-01T00:52:06+02:00",
    "personal": {
        "submitter_name": "mibig.secondarymetabolites.org",
        "submitter_institution": "MIBiG",
        "submitter_email": "info@mibig.secondarymetabolites.org"
    }
}