{
    "changelog": [
        {
            "comments": [
                "Migrated from v1.4"
            ],
            "version": "2.0"
        }
    ],
    "cluster": {
        "biosyn_class": [
            "Other"
        ],
        "compounds": [
            {
                "compound": "spiroindimicins"
            },
            {
                "compound": "indimicins"
            },
            {
                "compound": "lynamicins"
            }
        ],
        "loci": {
            "accession": "KY750719.1",
            "completeness": "Unknown"
        },
        "mibig_accession": "BGC0001782",
        "minimal": true,
        "ncbi_tax_id": "1109743",
        "organism_name": "Streptomyces sp. SCSIO 03032",
        "publications": [
            "pubmed:28620687"
        ]
    },
    "submitter": {
        "email": "info@mibig.secondarymetabolites.org",
        "institution": "MIBiG",
        "name": "mibig.secondarymetabolites.org"
    }
}