{
    "changelog": [
        {
            "comment": "Submitted",
            "version": "2.0"
        }
    ],
    "cluster": {
        "biosyn_class": [
            "NRP"
        ],
        "compounds": [
            {
                "compound": "albachelin",
                "database_id": []
            }
        ],
        "loci": {
            "accession": "NZ_KB913032.1",
            "completeness": "Unknown",
            "end_coord": 6464849,
            "evidence": [],
            "organism": "Amycolatopsis alba DSM 44262",
            "start_coord": 6431187,
            "taxonomy": [
                "Bacteria",
                "Actinobacteria",
                "Pseudonocardiales",
                "Pseudonocardiaceae",
                "Amycolatopsis"
            ]
        },
        "mibig_accession": "BGC0001211",
        "minimal": true,
        "publications": [
            "pubmed:25749409"
        ]
    },
    "submitter": {
        "email": "info@mibig.secondarymetabolites.org",
        "institution": "MIBiG",
        "name": "mibig.secondarymetabolites.org"
    }
}