{
    "submitter": {
        "name": "mibig.secondarymetabolites.org",
        "institution": "MIBiG",
        "email": "info@mibig.secondarymetabolites.org"
    },
    "changelog": [
        {
            "version": "2.0",
            "comment": "Submitted"
        }
    ],
    "cluster": {
        "compounds": [
            {
                "compound": "xanthoferrin",
                "database_id": ""
            }
        ],
        "loci": {
            "accession": "AE013598.1",
            "start_coord": 1377590,
            "end_coord": 1387887,
            "completeness": "Unknown",
            "evidence": []
        },
        "mibig_accession": "BGC0001408",
        "publications": [
            "pubmed:20382771"
        ],
        "minimal": true,
        "biosyn_class": [
            "Other"
        ],
        "other": {
            "subclass": "Unknown"
        }
    }
}