{
    "changelog": [
        {
            "comment": "Submitted",
            "version": "2.0"
        }
    ],
    "cluster": {
        "biosyn_class": [
            "Saccharide"
        ],
        "compounds": [
            {
                "compound": "polysaccharide B",
                "database_id": []
            }
        ],
        "loci": {
            "accession": "AF285774.2",
            "completeness": "Unknown",
            "evidence": [],
            "organism": "Bacteroides fragilis",
            "taxonomy": [
                "Bacteria",
                "Bacteroidetes",
                "Bacteroidia",
                "Bacteroidales",
                "Bacteroidaceae",
                "Bacteroides"
            ]
        },
        "mibig_accession": "BGC0001411",
        "minimal": true,
        "publications": [
            "pubmed:11035722"
        ]
    },
    "submitter": {
        "email": "info@mibig.secondarymetabolites.org",
        "institution": "MIBiG",
        "name": "mibig.secondarymetabolites.org"
    }
}