{
    "general_params": {
        "compounds": [
            {
                "compound": "anantin B1"
            },
            {
                "compound": "anantin B2"
            }
        ],
        "loci": {
            "accession": "NZ_JOAW01000056.1",
            "start_coord": 3033,
            "end_coord": 5863,
            "conn_comp_cluster": [
                "Unknown"
            ],
            "complete": "Unknown"
        },
        "mibig_accession": "BGC0001506",
        "biosyn_class": [
            "RiPP"
        ],
        "minimal": true,
        "publications": [
            "pubmed:28244986"
        ]
    },
    "personal": {
        "submitter_name": "mibig.secondarymetabolites.org",
        "submitter_institution": "MIBiG",
        "submitter_email": "mibig@secondarymetabolites.org"
    },
    "changelogs": [
        {
            "version": "2.0",
            "comment": "Submitted"
        }
    ]
}